.git-blame-ignore-revs
.gitignore
.gitlab-ci.yml
.ruff.toml
CHANGELOG.rst
CONTRIBUTING.md
LICENSE.txt
MANIFEST.in
README.md
pyproject.toml
setup.py
tox.ini
.github/workflows/sdist.yml
.github/workflows/tox.yml
brainbuilder/__init__.py
brainbuilder/cell_orientations.py
brainbuilder/cell_positions.py
brainbuilder/exceptions.py
brainbuilder/masks.py
brainbuilder/poisson_disc_sampling.py
brainbuilder/targets.py
brainbuilder/version.py
brainbuilder.egg-info/PKG-INFO
brainbuilder.egg-info/SOURCES.txt
brainbuilder.egg-info/dependency_links.txt
brainbuilder.egg-info/entry_points.txt
brainbuilder.egg-info/requires.txt
brainbuilder.egg-info/top_level.txt
brainbuilder/app/__init__.py
brainbuilder/app/__main__.py
brainbuilder/app/_utils.py
brainbuilder/app/atlases.py
brainbuilder/app/cells.py
brainbuilder/app/mvd3.py
brainbuilder/app/nrn.py
brainbuilder/app/sonata.py
brainbuilder/app/syn2.py
brainbuilder/app/targets.py
brainbuilder/utils/__init__.py
brainbuilder/utils/bbp.py
brainbuilder/utils/deprecate.py
brainbuilder/utils/random.py
brainbuilder/utils/sonata/__init__.py
brainbuilder/utils/sonata/clip.py
brainbuilder/utils/sonata/convert.py
brainbuilder/utils/sonata/curate.py
brainbuilder/utils/sonata/reindex.py
brainbuilder/utils/sonata/split_population.py
brainbuilder/utils/sonata/write_config.py
doc/Makefile
doc/source/api.rst
doc/source/changelog.rst
doc/source/cli.rst
doc/source/conf.py
doc/source/index.rst
doc/source/reindex_sonata.rst
doc/source/split-subcircuit.rst
doc/source/_static/.gitignore
doc/source/_static/reindex_morphology.svg
scripts/reindex_alternative.py
tests/functional/test_cell_positions_and_orientations.py
tests/functional/test_sonata_curate.py
tests/unit/test_add_subregion_property.py
tests/unit/test_app_cells.py
tests/unit/test_bbp.py
tests/unit/test_cell_orientations.py
tests/unit/test_cell_positions.py
tests/unit/test_mini_frequencies.py
tests/unit/test_poisson_disc_sampling.py
tests/unit/test_random.py
tests/unit/test_targets.py
tests/unit/data/builderConnectivityRecipeAllPathways.xml
tests/unit/data/builderRecipeAllPathways.xml
tests/unit/data/builderRecipeAllPathways_with_lattice.xml
tests/unit/data/cellRecipe.xml
tests/unit/data/cell_composition_v1.yaml
