Metadata-Version: 2.4
Name: brainbuilder
Version: 0.20.2
Summary: BrainBuilder is a tool to define the cells that will compose a circuit.
Author: Blue Brain Project, EPFL
License: Apache-2.0
Project-URL: Homepage, https://github.com/BlueBrain/brainbuilder
Project-URL: Repository, https://github.com/BlueBrain/brainbuilder.git
Project-URL: Documentation, https://github.com/BlueBrain/brainbuilder
Project-URL: Tracker, https://github.com/BlueBrain/brainbuilder/issues
Classifier: Development Status :: 2 - Pre-Alpha
Classifier: Intended Audience :: Education
Classifier: Intended Audience :: Science/Research
Classifier: Programming Language :: Python
Classifier: Programming Language :: Python :: 3
Classifier: Programming Language :: Python :: 3.8
Classifier: Programming Language :: Python :: 3.9
Classifier: Programming Language :: Python :: 3.10
Classifier: Programming Language :: Python :: 3.11
Classifier: Programming Language :: Python :: 3.12
Classifier: Topic :: Scientific/Engineering :: Bio-Informatics
Requires-Python: >=3.8
License-File: LICENSE.txt
Requires-Dist: bluepysnap>=1.0.3
Requires-Dist: click<9.0,>=7.0
Requires-Dist: h5py>=3.1.0
Requires-Dist: joblib>=1.0.1
Requires-Dist: jsonschema>=3.2.0
Requires-Dist: libsonata>=0.1.6
Requires-Dist: lxml>=3.3
Requires-Dist: morphio<4,>=3
Requires-Dist: numpy>=1.9
Requires-Dist: pandas>=1.0.0
Requires-Dist: pyyaml>=5.3.1
Requires-Dist: scipy>=0.13
Requires-Dist: tqdm>=4.0
Requires-Dist: voxcell>=3.1.1
Provides-Extra: all
Provides-Extra: reindex
Dynamic: license-file
